{
  "schema": "vela.event.v0.1",
  "id": "vev_2387e701d87b7354",
  "kind": "statement.attested",
  "target": {
    "type": "finding",
    "id": "vf_1a344718eb499768"
  },
  "actor": {
    "id": "reviewer:will-blair",
    "type": "human"
  },
  "timestamp": "2026-07-02T14:43:10.033417+00:00",
  "reason": "statement faithfulness attestation",
  "before_hash": "sha256:null",
  "after_hash": "sha256:null",
  "payload": {
    "attestation": {
      "attested_at": "2026-07-02T14:43:10.033385+00:00",
      "attested_by": "reviewer:will-blair",
      "formal_ref": "FormalConjectures/ErdosProblems/476.lean@4e4447c450b6",
      "formal_statement_hash": "38f02304abee9ea9a84f1002c03c98c3ff2c2c4d0f0174ebea9861df68e6c027",
      "id": "vsa_590ee5f723b17f6d",
      "informal_ref": "erdosproblems.com/476",
      "note": "batch-2c statement (PR #4346) for Erdős 476",
      "schema": "vela.statement_attestation.v0.1",
      "signature": "d4630020224cd1545c3edded4ec3dd034988ecba8cd35aec610b9466996c2b02c6563524395554bc0485c95ed1ce47c4b45abff61b63e1568723f31044b51607",
      "signer_pubkey_hex": "4892f93877e637b5f59af31d9ec6704814842fb278cacb0eb94704baef99455e",
      "target": "vf_1a344718eb499768",
      "verdict": "faithful"
    }
  },
  "caveats": [],
  "signature": "v1:fb9b8cbae23996ac1cd1d20b5a903501106a0150472ce0f7d7b64323093935d9796db3eb0912d5a7005af73103b24e8fee44ea5750b8513337c614db3325ae0f"
}