{
  "schema": "vela.event.v0.1",
  "id": "vev_0136daf56c38f565",
  "kind": "statement.attested",
  "target": {
    "type": "finding",
    "id": "vf_dcfea9b433b49cd2"
  },
  "actor": {
    "id": "reviewer:will-blair",
    "type": "human"
  },
  "timestamp": "2026-07-01T21:12:46.905477+00:00",
  "reason": "statement faithfulness attestation",
  "before_hash": "sha256:null",
  "after_hash": "sha256:null",
  "payload": {
    "attestation": {
      "attested_at": "2026-07-01T21:12:46.905458+00:00",
      "attested_by": "reviewer:will-blair",
      "formal_ref": "campaign-draft:statements/93/93.lean",
      "formal_statement_hash": "605bed8c90bb00478c8c577af45d63f1a4dec4f16414688c75a01312f332da9c",
      "id": "vsa_705d7d58a8fe1816",
      "informal_ref": "erdosproblems.com/93",
      "note": "campaign draft; machine verdict on hosted proof: unconditional (plby)",
      "schema": "vela.statement_attestation.v0.1",
      "signature": "727d2b4cd7ded6a85d5a6f110e96cbcf866371275764949aa6b9db78b82741e8bab847b06db47cd0e408808397cdfb2fcbb28cf8a4beff38ceaa687475412f02",
      "signer_pubkey_hex": "4892f93877e637b5f59af31d9ec6704814842fb278cacb0eb94704baef99455e",
      "target": "vf_dcfea9b433b49cd2",
      "verdict": "faithful"
    }
  },
  "caveats": [],
  "signature": "v1:2c92859ea7a4b004663b104c01daf7ef775d3879bb6cdf196af2de70ffacbd90659a22574da056cc5316d947a96fa58ce565a796a4623e4bf32e66193314f208"
}