{
  "schema": "vela.event.v0.1",
  "id": "vev_6409f30a0bf6624d",
  "kind": "attempt.deposited",
  "target": {
    "type": "attempt",
    "id": "vat_564c252bfd8e3f22"
  },
  "actor": {
    "id": "agent:erdos-history-import",
    "type": "agent"
  },
  "timestamp": "2026-07-13T18:48:50.044521+00:00",
  "reason": "historical attempt import from vela-science/erdos-frontier@121807e20b06eb8148f594dfe13e440181252b0f:attack/attempt-ledger.v2.json (provenance, not a verdict)",
  "before_hash": "sha256:null",
  "after_hash": "sha256:null",
  "payload": {
    "attempt": {
      "attempt_id": "vat_564c252bfd8e3f22",
      "claim": "PROVEN (#488, |A|=4 case): for any A={a<b<c<d} and all m>n>=d, F(m)/m<2F(n)/n. #488 now holds for |A|<=4. AND the natural general strategy is PROVABLY DEAD (GPT-Pro, Opus-verified): general |A|=k needs a fundamentally different bound.",
      "claim_digest": "fce697c1510a2204",
      "claimed_status": "proof_complete",
      "deliverable_grade": "partial_proof",
      "detail": "Proof (GPT-Pro, Opus-verified 0 viol in 31,441 checks). Reduce nonprimitive 4-sets to |A|<=3; for primitive antichains prove 2F(n)>(n+1)S (S=sum 1/a_i) via a TWO-SHIFT injection: each x with nu(x)>=3 has smallest covering element alpha and x>3*alpha; x-alpha and x-2*alpha are not divisible by any OTHER covering element (primitivity); for nu=4 (no outside element) BOTH are alpha-only (2 singletons); for nu=3 (one outside element h) h can spoil at most one (else h|alpha), so >=1 singleton. Injection is injective + avoids the 4 base points => N1>=N3+2N4+4 (>=+5 when lcm(A)|n+1). With (n+1)S-M<=4 (eq iff lcm|n+1), get 2F(n)>(n+1)S; then F(m)/m<=S<2F(n)/(n+1)<2F(n)/n. GENERAL CASE IS A WALL (two proven obstructions, Opus-verified): (1) the S-lemma 2F(n)>(n+1)S is FALSE for large k -- A={primes<=277}, n=277: S=2.00235>2 so 2F=552<(n+1)S=556.65 (does NOT disprove #488, since F(m)/m<=1 saves it, but kills the F(m)/m<=S route). (2) the injection target N1-sum_{j>=3}(j-2)N_j>=k is FALSE -- same example gives N1-N3-2N4=23<k=59. (3) the two-shift injection itself breaks at k>=5: A={2,3,5,7,13}, x=30 has x-2=28 (|7) and x-4=26 (|13) BOTH spoiled by two outside elements. So a general proof must use the cap F(m)/m<=1 and the actual union density, NOT S=sum 1/a_i. STATUS: #488 proven for |A|<=4 (clean, verified, ours). General |A|=k OPEN and requiring a fundamentally different bound (the natural shifted-density approach is provably insufficient). Pushing |A|=5 would need a new injection handling 2 outside elements; general needs the union-density cap.",
      "kind": "partial_proof",
      "problem": 488,
      "provenance": {
        "date": "2026-06-04"
      },
      "reusable_for": "#488 |A|<=4 proven (two-shift injection); the general approach is provably dead (S-lemma + injection-target both false for large k)",
      "schema": "vela.attempt.v0.1",
      "signature": "d23cca4bd5d1cf162462a2f66dec5e84ea944ef8f074aa02bbe77fe5e90a365c034b9d99687c75b7db77873edde86729c6ffc75ba333b03e9680b5a6c785d305",
      "signer_pubkey_hex": "bc6382b722d59bdded6b9f4796816f4071c2c12b14ed3ffd0827d7b40e29e570"
    },
    "import": {
      "schema": "vela.attempt-import.v1",
      "source_attempt_id": "vat_564c252bfd8e3f22",
      "source_legacy_id": "att_98c7ccd8a1f8dbc5",
      "source_ref": "vela-science/erdos-frontier@121807e20b06eb8148f594dfe13e440181252b0f:attack/attempt-ledger.v2.json"
    }
  },
  "caveats": [
    "A signed banked attempt. Trust is earned via its verifier_attachments + the gate, never from claimed_status."
  ],
  "signature": "v1:b525e5d68d59431c5cd709f4cdb827ba48e261f74cfd9f0f073fdf33e80a1abbb1458d463929559e07d4a59f4c7ce9c9cb03d22e8d63b14d5cb7aab348969805"
}