{"accepted":[{"assertion":"Formal-Conjectures statement: Erdos1167.erdos_1167 https://google-deepmind.github.io/formal-conjectures/theorem/?name=Erdos1167.erdos_1167.","id":"vf_948cf4ab27a5b61e","trust":"signed","type":"theoretical"},{"assertion":"Erdős Problem #1167: declared status 'open'. Formalized: yes. Prize: no. Tags: probability, set theory.","id":"vf_f2a7a47f0ef2b8ea","trust":"signed","type":"theoretical"}],"accepted_activity":false,"activity":[],"activity_types":[],"attempt_count":0,"banked_attempt_count":0,"commits":[],"dependency_impact":"none","detail_url":"problems/1167.json","draft_proposals":[],"edges":[{"evidence":"Problem identity derived from the accepted finding's pinned source anchor.","inferred":true,"relation":"describes","source":"vf_948cf4ab27a5b61e","source_root":"sha256:1faedc24f040a60a22177b456c74b969a61ce8836082297b1835797a57b4fa56","target":"erdos:1167","trust":"signed"},{"evidence":"Materialized typed link between accepted findings.","inferred":true,"relation":"synthesized_from","source":"vf_948cf4ab27a5b61e","source_root":"sha256:1faedc24f040a60a22177b456c74b969a61ce8836082297b1835797a57b4fa56","target":"vf_f2a7a47f0ef2b8ea","trust":"signed"},{"evidence":"Problem identity derived from the accepted finding's pinned source anchor.","inferred":true,"relation":"describes","source":"vf_f2a7a47f0ef2b8ea","source_root":"sha256:1faedc24f040a60a22177b456c74b969a61ce8836082297b1835797a57b4fa56","target":"erdos:1167","trust":"signed"}],"external_references":[],"formal_conjectures_activity":null,"frontier_id":"vfr_0a25edabc16db143","frontier_root":"sha256:1faedc24f040a60a22177b456c74b969a61ce8836082297b1835797a57b4fa56","label":"Erdős 1167","lenses":{"all_authored":false,"current_record":false,"mathematical_work":false,"research_plus_scouting":false},"lifecycle":"unstarted","location":"reference_only","machine_status":"not_checked","mathematical_scope":"not_applicable","method_channels":[],"nodes":[{"id":"erdos:1167","inferred":false,"kind":"problem","label":"Erdős 1167","path":"site/problems/1167.json","plane":"reference","source_root":"sha256:1faedc24f040a60a22177b456c74b969a61ce8836082297b1835797a57b4fa56","trust":"declared","upstream_state":"open"},{"id":"vf_948cf4ab27a5b61e","inferred":false,"kind":"finding","label":"Formal-Conjectures statement: Erdos1167.erdos_1167 https://google-deepmind.github.io/formal-conjectures/theorem/?name=Erdos1167.erdos_1167.","path":"frontier.json#vf_948cf4ab27a5b61e","plane":"state","source_root":"sha256:1faedc24f040a60a22177b456c74b969a61ce8836082297b1835797a57b4fa56","trust":"signed"},{"id":"vf_f2a7a47f0ef2b8ea","inferred":false,"kind":"finding","label":"Erdős Problem #1167: declared status 'open'. Formalized: yes. Prize: no. Tags: probability, set theory.","path":"frontier.json#vf_f2a7a47f0ef2b8ea","plane":"state","source_root":"sha256:1faedc24f040a60a22177b456c74b969a61ce8836082297b1835797a57b4fa56","trust":"signed"}],"problem":1167,"producers":[],"proof_artifacts":[],"proposal_state_hash":"sha256:e69b38037814f2e8ca826942cfc50ab370993889be2913cac1c0b3e77711160f","receipts":[],"recovered_record_count":0,"repositories":[],"residual_obligations":[],"review_obligations":[],"schema":"erdos-frontier.problem-work.v1","sources":[],"statement":{"formal_statement":{"linked_proof":false,"theorem":"Erdos1167.erdos_1167","url":"https://google-deepmind.github.io/formal-conjectures/theorem/?name=Erdos1167.erdos_1167"},"statement_fidelity":"pending","upstream_state":"open","upstream_url":"https://www.erdosproblems.com/1167"},"statement_fidelity":"pending","summary":"Reference corpus entry; no authored work recorded.","trust":"declared","upstream_state":"open","url":"https://www.erdosproblems.com/1167","witnesses":[]}
