{"accepted":[{"assertion":"Erdős Problem #411: declared status 'open'. Formalized: no. Let $g_1=g(n)=n+\\phi(n)$ and $g_k(n)=g(g_{k-1}(n))$. For which $n$ and $r$ is it true that $g_{k+r}(n)=2g_k(n)$ for all large $k$? Current best: Selfridge and Weintraub found solutions to $g_{k+9}(n)=9g_k(n)$ and Weintraub found\\[g_{k+25}(3114)=729g_k(3114)\\]for all $k\\geq 6$. Steinerberger \\cite{St25} has observed that, for $r=2$, this problem is equivalent to asking for solutions to\\[\\phi(n)+\\phi(n+\\phi(n))=n,\\]and has shown that if this holds then either the odd part of $n$ is in $\\{1,3,5,7,35,47\\}$, or is equal to $8m+7$ or $6m+5$, where $8m+7\\geq 10^{10}$ is a prime number and $\\phi(6m+5)=4m+4$. Cambie conjectures that the only solutions have $r=2$ and $n=2^lp$ for some $l\\geq 1$ and $p\\in \\{2,3,5,7,35,47\\}$. Cambie has shown this problem is reducible to the question of which integers $r,t\\geq 1$ and primes $p\\equiv 7\\pmod{8}$ satisfy $g_k(2p^t)=4p^t$, and conjectures there are no solutions to this except when $t=1$ and $p\\in \\{7,47\\}$. Prize: no. OEIS: A383044. Tags: iterated functions, number theory.","id":"vf_a9877a116ebd3e1e","trust":"signed","type":"theoretical"}],"accepted_activity":false,"activity":[],"activity_types":[],"attempt_count":0,"banked_attempt_count":0,"commits":[],"dependency_impact":"none","detail_url":"problems/411.json","draft_proposals":[],"edges":[{"evidence":"Problem identity derived from the accepted finding's pinned source anchor.","inferred":true,"relation":"describes","source":"vf_a9877a116ebd3e1e","source_root":"sha256:d3db36661e28b7570fc8704bf8455b80d8382beded47d069f2c386144d90a238","target":"erdos:411","trust":"signed"}],"external_references":[],"formal_conjectures_activity":null,"frontier_id":"vfr_0a25edabc16db143","frontier_root":"sha256:d3db36661e28b7570fc8704bf8455b80d8382beded47d069f2c386144d90a238","label":"Erdős 411","lenses":{"all_authored":false,"current_record":false,"mathematical_work":false,"research_plus_scouting":false},"lifecycle":"unstarted","location":"reference_only","machine_status":"not_checked","mathematical_scope":"not_applicable","method_channels":[],"nodes":[{"id":"erdos:411","inferred":false,"kind":"problem","label":"Erdős 411","path":"site/problems/411.json","plane":"reference","source_root":"sha256:d3db36661e28b7570fc8704bf8455b80d8382beded47d069f2c386144d90a238","trust":"declared","upstream_state":"open"},{"id":"vf_a9877a116ebd3e1e","inferred":false,"kind":"finding","label":"Erdős Problem #411: declared status 'open'. Formalized: no. Let $g_1=g(n)=n+\\phi(n)$ and $g_k(n)=g(g_{k-1}(n))$. For which $n$ and $r$ is it true that $g_{k+r}(n)=2g_k(n)$ for all…","path":"frontier.json#vf_a9877a116ebd3e1e","plane":"state","source_root":"sha256:d3db36661e28b7570fc8704bf8455b80d8382beded47d069f2c386144d90a238","trust":"signed"}],"problem":411,"producers":[],"proof_artifacts":[],"proposal_state_hash":"sha256:603efb0a800cb4d968d769956086ed9c6f5b00e86730c8dcc0cc3eba6141f8de","receipts":[],"recovered_record_count":0,"repositories":[],"residual_obligations":[],"review_obligations":[],"schema":"erdos-frontier.problem-work.v1","sources":[],"statement":{"formal_statement":null,"statement_fidelity":"not_assessed","upstream_state":"open","upstream_url":"https://www.erdosproblems.com/411"},"statement_fidelity":"not_assessed","summary":"Reference corpus entry; no authored work recorded.","trust":"declared","upstream_state":"open","url":"https://www.erdosproblems.com/411","witnesses":[]}
